fluidattacks_target_warehouse/__init__.py
fluidattacks_target_warehouse/_logger.py
fluidattacks_target_warehouse/_s3.py
fluidattacks_target_warehouse/_utils.py
fluidattacks_target_warehouse/grouper.py
fluidattacks_target_warehouse/py.typed
fluidattacks_target_warehouse/_cli/__init__.py
fluidattacks_target_warehouse/_cli/_append.py
fluidattacks_target_warehouse/_cli/_decode.py
fluidattacks_target_warehouse/_cli/_recreate.py
fluidattacks_target_warehouse/data_schema/__init__.py
fluidattacks_target_warehouse/data_schema/_data_types/__init__.py
fluidattacks_target_warehouse/data_schema/_data_types/_integer.py
fluidattacks_target_warehouse/data_schema/_data_types/_number.py
fluidattacks_target_warehouse/data_schema/_data_types/_string.py
fluidattacks_target_warehouse/data_schema/duplicates/__init__.py
fluidattacks_target_warehouse/data_schema/duplicates/_classifier.py
fluidattacks_target_warehouse/executor/__init__.py
fluidattacks_target_warehouse/executor/_generic.py
fluidattacks_target_warehouse/executor/_input.py
fluidattacks_target_warehouse/executor/_output.py
fluidattacks_target_warehouse/loader/__init__.py
fluidattacks_target_warehouse/loader/_core.py
fluidattacks_target_warehouse/loader/_loaders.py
fluidattacks_target_warehouse/loader/_handlers/__init__.py
fluidattacks_target_warehouse/loader/_handlers/_schema.py
fluidattacks_target_warehouse/loader/_handlers/_state.py
fluidattacks_target_warehouse/loader/_handlers/_records/__init__.py
fluidattacks_target_warehouse/loader/_handlers/_records/_handler.py
fluidattacks_target_warehouse/loader/_handlers/_records/_stream_records.py
fluidattacks_target_warehouse/loader/_truncate/__init__.py
fluidattacks_target_warehouse/loader/_truncate/utf8_truncation/__init__.py
fluidattacks_target_warehouse/loader/_truncate/utf8_truncation/core.py
fluidattacks_target_warehouse/strategy/__init__.py
fluidattacks_target_warehouse/strategy/_core.py
fluidattacks_target_warehouse/strategy/_move_data.py
fluidattacks_target_warehouse-2.1.0.dist-info/entry_points.txt
fluidattacks_target_warehouse-2.1.0.dist-info/WHEEL
fluidattacks_target_warehouse-2.1.0.dist-info/METADATA
fluidattacks_target_warehouse-2.1.0.dist-info/RECORD
