Metadata-Version: 2.4
Name: fluidattacks_target_warehouse
Version: 2.1.0
Summary: Singer target for fluidattacks warehouse
Author-email: Product Team <development@fluidattacks.com>
Requires-Python: >=3.11
Classifier: License :: OSI Approved :: MIT License
Requires-Dist: boto3 >=1.17.104, <2.0.0
Requires-Dist: click >=8.1.3, <9.0.0
Requires-Dist: fluidattacks-connection-manager >=2.0.0, <3.0.0
Requires-Dist: fluidattacks-etl-utils >=2.0.0, <3.0.0
Requires-Dist: fa-purity >=2.1.0, <3.0.0
Requires-Dist: fa-singer-io >=2.0.2, <4.0.0
Requires-Dist: mypy-boto3-s3 >=1.28.55, <2.0.0
Requires-Dist: redshift-client >=8.1.1, <9.0.0
Requires-Dist: snowflake-client >=3.2.3, <4.0.0
Requires-Dist: fluidattacks-utils-logger >=3.0.0, <4.0.0
